[
  {
    "name": "Ethereum",
    "symbol": "ETH",
    "timestamp": "2022-12-10 18:03:42",
    "validators": 486475,
    "nodes": 8120,
    "total": 494595,
    "source": "https://beaconcha.in",
    "market_cap_rank": 2,
    "market_cap": 153488527802,
    "volume": 3530917598,
    "nodediff": 0,
    "nodediffper": 0,
    "validatordiff": 830,
    "validatordiffper": 0.17,
    "totaldiff": 830,
    "totaldiffper": 0.17,
    "rank": 1,
    "created": "2022-12-11 14:02:12",
    "chaintype": "PoS"
  },
  {
    "name": "Bitcoin",
    "symbol": "BTC",
    "timestamp": "2022-12-11 14:01:23",
    "validators": 0,
    "nodes": 11099,
    "total": 11099,
    "source": "https://bitnodes.io",
    "consensus_long": "Proof of Work",
    "consensus_short": "PoW",
    "retrieved": "2022-12-11 14:02:08",
    "market_cap_rank": 1,
    "market_cap": 329714951043,
    "volume": 14236063715,
    "nodediff": -4524,
    "nodediffper": -28.96,
    "validatordiff": 0,
    "validatordiffper": 0,
    "totaldiff": -4524,
    "totaldiffper": -28.96,
    "rank": 2,
    "created": "2022-12-11 14:02:12",
    "chaintype": "PoW"
  },
  {
    "name": "Zcash",
    "symbol": "ZEC",
    "timestamp": "2022-12-11 10:05:57",
    "validators": 0,
    "nodes": 8009,
    "total": 8009,
    "source": "https://blockchair.com/zcash/nodes",
    "market_cap_rank": 65,
    "market_cap": 594295261,
    "volume": 21990377,
    "nodediff": 125,
    "nodediffper": 1.59,
    "validatordiff": 0,
    "validatordiffper": 0,
    "totaldiff": 125,
    "totaldiffper": 1.59,
    "rank": 3,
    "created": "2022-12-11 14:02:12",
    "chaintype": "PoW"
  },
  {
    "name": "Filecoin",
    "symbol": "FIL",
    "timestamp": "2022-10-04 18:16:55",
    "validators": 0,
    "nodes": 4049,
    "total": 4049,
    "source": "https://filfox.info/en",
    "market_cap_rank": 38,
    "market_cap": 1638580071,
    "volume": 95428368,
    "nodediff": 7,
    "nodediffper": 0.17,
    "validatordiff": 0,
    "validatordiffper": 0,
    "totaldiff": 7,
    "totaldiffper": 0.17,
    "rank": 4,
    "created": "2022-12-11 14:02:12",
    "chaintype": "PoW"
  },
  {
    "name": "Theta",
    "symbol": "THETA",
    "timestamp": "2022-12-11 10:05:37",
    "validators": 3264,
    "nodes": 0,
    "total": 3264,
    "source": "https://explorer.thetatoken.org",
    "market_cap_rank": 49,
    "market_cap": 861160437,
    "volume": 11876023,
    "nodediff": 0,
    "nodediffper": 0,
    "validatordiff": 3,
    "validatordiffper": 0.09,
    "totaldiff": 3,
    "totaldiffper": 0.09,
    "rank": 5,
    "created": "2022-12-11 14:02:12",
    "chaintype": "PoS"
  },
  {
    "name": "Elrond",
    "symbol": "EGLD",
    "timestamp": "2022-10-04 14:19:17",
    "validators": 3178,
    "nodes": 0,
    "total": 3178,
    "source": "https://elrondscan.com/validators",
    "market_cap_rank": 44,
    "market_cap": 1286183023,
    "volume": 82836262,
    "nodediff": 0,
    "nodediffper": 0,
    "validatordiff": -5,
    "validatordiffper": -0.16,
    "totaldiff": -5,
    "totaldiffper": -0.16,
    "rank": 6,
    "created": "2022-12-11 14:02:12",
    "chaintype": "PoS"
  },
  {
    "name": "Zilliqa",
    "symbol": "ZIL",
    "timestamp": "2022-09-16 10:05:49",
    "validators": 0,
    "nodes": 2400,
    "total": 2400,
    "source": "https://viewblock.io/zilliqa",
    "market_cap_rank": 85,
    "market_cap": 502689681,
    "volume": 34320901,
    "nodediff": 0,
    "nodediffper": 0,
    "validatordiff": -21,
    "validatordiffper": -100.0,
    "totaldiff": -21,
    "totaldiffper": -0.87,
    "rank": 7,
    "created": "2022-12-11 14:02:12",
    "chaintype": "PoW"
  },
  {
    "name": "Monero",
    "symbol": "XMR",
    "timestamp": "2022-10-04 14:24:45",
    "validators": 0,
    "nodes": 2079,
    "total": 2079,
    "source": "https://monerohash.com/nodes-distribution.html",
    "market_cap_rank": 30,
    "market_cap": 2656388823,
    "volume": 70526323,
    "nodediff": 69,
    "nodediffper": 3.43,
    "validatordiff": 0,
    "validatordiffper": 0,
    "totaldiff": 69,
    "totaldiffper": 3.43,
    "rank": 8,
    "created": "2022-12-11 14:02:12",
    "chaintype": "PoW"
  },
  {
    "name": "Solana",
    "symbol": "SOL",
    "timestamp": "2022-12-11 10:05:50",
    "validators": 1883,
    "nodes": 0,
    "total": 1883,
    "source": "https://www.validators.app",
    "market_cap_rank": 18,
    "market_cap": 4996923132,
    "volume": 106933266,
    "nodediff": 0,
    "nodediffper": 0,
    "validatordiff": 0,
    "validatordiffper": 0,
    "totaldiff": 0,
    "totaldiffper": 0,
    "rank": 9,
    "created": "2022-12-11 14:02:12",
    "chaintype": "PoS"
  },
  {
    "name": "Avalanche",
    "symbol": "AVAX",
    "timestamp": "2022-12-11 14:02:08",
    "validators": 1205,
    "nodes": 0,
    "total": 1205,
    "source": "https://avascan.info",
    "consensus_long": "Proof of Stake",
    "consensus_short": "PoS",
    "market_cap_rank": 20,
    "market_cap": 4174174143,
    "volume": 89443830,
    "nodediff": 0,
    "nodediffper": 0,
    "validatordiff": -1,
    "validatordiffper": -0.08,
    "totaldiff": -1,
    "totaldiffper": -0.08,
    "rank": 10,
    "created": "2022-12-11 14:02:12",
    "chaintype": "PoS"
  },
  {
    "name": "Litecoin",
    "symbol": "LTC",
    "timestamp": "2022-12-10 22:02:53",
    "validators": 0,
    "nodes": 1051,
    "total": 1051,
    "source": "https://blockchair.com/en/litecoin/nodes",
    "market_cap_rank": 13,
    "market_cap": 5487014073,
    "volume": 289824182,
    "nodediff": -1,
    "nodediffper": -0.1,
    "validatordiff": 0,
    "validatordiffper": 0,
    "totaldiff": -1,
    "totaldiffper": -0.1,
    "rank": 11,
    "created": "2022-12-11 14:02:12",
    "chaintype": "PoW"
  },
  {
    "name": "Kusama",
    "symbol": "KSM",
    "timestamp": "2022-12-10 22:02:49",
    "validators": 1000,
    "nodes": 0,
    "total": 1000,
    "source": "https://kusama.subscan.io/validator",
    "market_cap_rank": 119,
    "market_cap": 266408737,
    "volume": 8127436,
    "nodediff": 0,
    "nodediffper": 0,
    "validatordiff": 0,
    "validatordiffper": 0,
    "totaldiff": 0,
    "totaldiffper": 0,
    "rank": 12,
    "created": "2022-12-11 14:02:12",
    "chaintype": "PoS"
  },
  {
    "name": "Dogecoin",
    "symbol": "DOGE",
    "timestamp": "2022-12-11 14:02:01",
    "validators": 0,
    "nodes": 883,
    "total": 883,
    "source": "https://blockchair.com/en/dogecoin/nodes",
    "market_cap_rank": 8,
    "market_cap": 13246658174,
    "volume": 267750555,
    "nodediff": 0,
    "nodediffper": 0,
    "validatordiff": 0,
    "validatordiffper": 0,
    "totaldiff": 0,
    "totaldiffper": 0,
    "rank": 13,
    "created": "2022-12-11 14:02:12",
    "chaintype": "PoW"
  },
  {
    "name": "Ripple",
    "symbol": "XRP",
    "timestamp": "2022-12-10 18:03:50",
    "validators": 116,
    "nodes": 682,
    "total": 798,
    "source": "https://livenet.xrpl.org/",
    "market_cap_rank": 7,
    "market_cap": 19602956119,
    "volume": 401198438,
    "nodediff": -3,
    "nodediffper": -0.44,
    "validatordiff": 0,
    "validatordiffper": 0,
    "totaldiff": -3,
    "totaldiffper": -0.37,
    "rank": 14,
    "created": "2022-12-11 14:02:12",
    "chaintype": "PoS"
  },
  {
    "name": "Bitcoin Cash",
    "symbol": "BCH",
    "timestamp": "2022-12-11 14:01:49",
    "validators": 0,
    "nodes": 739,
    "total": 739,
    "source": "https://cashnodes.io/",
    "consensus_long": "Proof of Work",
    "consensus_short": "PoW",
    "market_cap_rank": 29,
    "market_cap": 2102940066,
    "volume": 383630007,
    "nodediff": 4,
    "nodediffper": 0.54,
    "validatordiff": 0,
    "validatordiffper": 0,
    "totaldiff": 4,
    "totaldiffper": 0.54,
    "rank": 15,
    "created": "2022-12-11 14:02:12",
    "chaintype": "PoW"
  },
  {
    "name": "Ethereum Classic",
    "symbol": "ETC",
    "timestamp": "2022-12-10 18:03:41",
    "validators": 0,
    "nodes": 693,
    "total": 693,
    "source": "https://nodes.etc-network.info/nodes-interface/",
    "market_cap_rank": 27,
    "market_cap": 2673236012,
    "volume": 76826691,
    "nodediff": -79,
    "nodediffper": -10.23,
    "validatordiff": 0,
    "validatordiffper": 0,
    "totaldiff": -79,
    "totaldiffper": -10.23,
    "rank": 16,
    "created": "2022-12-11 14:02:12",
    "chaintype": "PoW"
  },
  {
    "name": "Internet Computer",
    "symbol": "ICP",
    "timestamp": "2022-12-10 18:03:54",
    "validators": 0,
    "nodes": 549,
    "total": 549,
    "source": "https://www.icpexplorer.org",
    "market_cap_rank": 38,
    "market_cap": 1218211179,
    "volume": 19343860,
    "nodediff": 0,
    "nodediffper": 0,
    "validatordiff": 0,
    "validatordiffper": 0,
    "totaldiff": 0,
    "totaldiffper": 0,
    "rank": 17,
    "created": "2022-12-11 14:02:12",
    "chaintype": "PoW"
  },
  {
    "name": "Waves",
    "symbol": "WAVES",
    "timestamp": "2022-10-03 22:03:17",
    "validators": 0,
    "nodes": 466,
    "total": 466,
    "source": "https://wavesexplorer.com/nodes",
    "market_cap_rank": 103,
    "market_cap": 378414123,
    "volume": 35614492,
    "nodediff": 0,
    "nodediffper": 0,
    "validatordiff": 0,
    "validatordiffper": 0,
    "totaldiff": 0,
    "totaldiffper": 0,
    "rank": 18,
    "created": "2022-12-11 14:02:12",
    "chaintype": "PoW"
  },
  {
    "name": "Flow",
    "symbol": "FLOW",
    "timestamp": "2022-10-04 18:18:10",
    "validators": 422,
    "nodes": 0,
    "total": 422,
    "source": "https://flowscan.org/staking/overview",
    "market_cap_rank": 35,
    "market_cap": 1770805620,
    "volume": 29399830,
    "nodediff": 0,
    "nodediffper": 0,
    "validatordiff": 0,
    "validatordiffper": 0,
    "totaldiff": 0,
    "totaldiffper": 0,
    "rank": 19,
    "created": "2022-12-11 14:02:12",
    "chaintype": "PoS"
  },
  {
    "name": "Tezos",
    "symbol": "XTZ",
    "timestamp": "2022-12-11 10:05:35",
    "validators": 408,
    "nodes": 0,
    "total": 408,
    "source": "https://tzstats.com",
    "market_cap_rank": 46,
    "market_cap": 922192964,
    "volume": 10029953,
    "nodediff": 0,
    "nodediffper": 0,
    "validatordiff": 0,
    "validatordiffper": 0,
    "totaldiff": 0,
    "totaldiffper": 0,
    "rank": 20,
    "created": "2022-12-11 14:02:12",
    "chaintype": "PoS"
  },
  {
    "name": "IOTA",
    "symbol": "MIOTA",
    "timestamp": "2022-10-03 22:04:00",
    "validators": 0,
    "nodes": 357,
    "total": 357,
    "source": "https://thetangle.org/nodes",
    "market_cap_rank": 60,
    "market_cap": 772554256,
    "volume": 13075791,
    "nodediff": -5,
    "nodediffper": -1.38,
    "validatordiff": 0,
    "validatordiffper": 0,
    "totaldiff": -5,
    "totaldiffper": -1.38,
    "rank": 21,
    "created": "2022-12-11 14:02:12",
    "chaintype": "PoW"
  },
  {
    "name": "Polkadot",
    "symbol": "POL",
    "timestamp": "2022-12-11 10:05:36",
    "validators": 297,
    "nodes": 0,
    "total": 297,
    "source": "https://polkadot.subscan.io/",
    "market_cap_rank": 11,
    "market_cap": 6235171565,
    "volume": 80281460,
    "nodediff": 0,
    "nodediffper": 0,
    "validatordiff": 0,
    "validatordiffper": 0,
    "totaldiff": 0,
    "totaldiffper": 0,
    "rank": 22,
    "created": "2022-12-11 14:02:12",
    "chaintype": "PoS"
  },
  {
    "name": "Algorand",
    "symbol": "ALGO",
    "timestamp": "2022-12-10 18:03:37",
    "validators": 223,
    "nodes": 0,
    "total": 223,
    "source": "https://metrics.algorand.org/#/decentralization/",
    "market_cap_rank": 31,
    "market_cap": 1643468936,
    "volume": 50789820,
    "nodediff": 0,
    "nodediffper": 0,
    "validatordiff": -1,
    "validatordiffper": -0.45,
    "totaldiff": -1,
    "totaldiffper": -0.45,
    "rank": 23,
    "created": "2022-12-11 14:02:12",
    "chaintype": "PoS"
  },
  {
    "name": "The Graph",
    "symbol": "GRT",
    "timestamp": "2022-10-04 18:17:03",
    "validators": 220,
    "nodes": 0,
    "total": 220,
    "source": "https://thegraph.com/explorer/network",
    "market_cap_rank": 62,
    "market_cap": 744655118,
    "volume": 14703637,
    "nodediff": 0,
    "nodediffper": 0,
    "validatordiff": 1,
    "validatordiffper": 0.46,
    "totaldiff": 1,
    "totaldiffper": 0.46,
    "rank": 24,
    "created": "2022-12-11 14:02:12",
    "chaintype": "PoS"
  },
  {
    "name": "XDC Network",
    "symbol": "XDC",
    "timestamp": "2022-12-10 22:03:05",
    "validators": 216,
    "nodes": 0,
    "total": 216,
    "source": "https://explorer.xinfin.network/masternodes",
    "market_cap_rank": 108,
    "market_cap": 304042038,
    "volume": 2706821,
    "nodediff": 0,
    "nodediffper": 0,
    "validatordiff": 0,
    "validatordiffper": 0,
    "totaldiff": 0,
    "totaldiffper": 0,
    "rank": 25,
    "created": "2022-12-11 14:02:12",
    "chaintype": "PoS"
  },
  {
    "name": "Everscale",
    "symbol": "EVER",
    "timestamp": "2022-12-11 14:02:05",
    "validators": 207,
    "nodes": 0,
    "total": 207,
    "source": "https://everscan.io/validators",
    "market_cap_rank": 335,
    "market_cap": 61398247,
    "volume": 3966487,
    "nodediff": 0,
    "nodediffper": 0,
    "validatordiff": -1,
    "validatordiffper": -0.48,
    "totaldiff": -1,
    "totaldiffper": -0.48,
    "rank": 26,
    "created": "2022-12-11 14:02:12",
    "chaintype": "PoS"
  },
  {
    "name": "Mina",
    "symbol": "MINA",
    "timestamp": "2022-10-03 22:03:04",
    "validators": 201,
    "nodes": 0,
    "total": 201,
    "source": "https://minaexplorer.com/",
    "market_cap_rank": 95,
    "market_cap": 411715952,
    "volume": 8973322,
    "nodediff": 0,
    "nodediffper": 0,
    "validatordiff": 19,
    "validatordiffper": 10.44,
    "totaldiff": 19,
    "totaldiffper": 10.44,
    "rank": 27,
    "created": "2022-12-11 14:02:12",
    "chaintype": "PoS"
  },
  {
    "name": "Celo",
    "symbol": "CELO",
    "timestamp": "2022-12-11 14:01:59",
    "validators": 179,
    "nodes": 0,
    "total": 179,
    "source": "https://thecelo.com/validators",
    "consensus_long": "Byzantine Fault Tolerant",
    "consensus_short": "BFT",
    "market_cap_rank": 113,
    "market_cap": 285765980,
    "volume": 10419943,
    "nodediff": 0,
    "nodediffper": 0,
    "validatordiff": 1,
    "validatordiffper": 0.56,
    "totaldiff": 1,
    "totaldiffper": 0.56,
    "rank": 28,
    "created": "2022-12-11 14:02:12",
    "chaintype": "PoS"
  },
  {
    "name": "Cosmos",
    "symbol": "ATOM",
    "timestamp": "2022-11-14 14:08:07",
    "validators": 175,
    "nodes": 0,
    "total": 175,
    "source": "https://www.mintscan.io/cosmos/validators",
    "consensus_long": "Byzantine Fault Tolerant",
    "consensus_short": "BFT",
    "market_cap_rank": 24,
    "market_cap": 3089992388,
    "volume": 271149786,
    "nodediff": 0,
    "nodediffper": 0,
    "validatordiff": 0,
    "validatordiffper": 0,
    "totaldiff": 0,
    "totaldiffper": 0,
    "rank": 29,
    "created": "2022-12-11 14:02:12",
    "chaintype": "PoS"
  },
  {
    "name": "Terra",
    "symbol": "LUNA",
    "timestamp": "2022-12-10 22:03:07",
    "validators": 172,
    "nodes": 0,
    "total": 172,
    "source": "https://terrasco.pe/mainnet/validators",
    "market_cap_rank": 112,
    "market_cap": 288366231,
    "volume": 16334267,
    "nodediff": 0,
    "nodediffper": 0,
    "validatordiff": 0,
    "validatordiffper": 0,
    "totaldiff": 0,
    "totaldiffper": 0,
    "rank": 30,
    "created": "2022-12-11 14:02:12",
    "chaintype": "PoS"
  },
  {
    "name": "GateToken",
    "symbol": "GT",
    "timestamp": "2022-12-10 18:03:55",
    "validators": 162,
    "nodes": 0,
    "total": 162,
    "source": "https://gatescan.org/",
    "market_cap_rank": 76,
    "market_cap": 522507234,
    "volume": 1532009,
    "nodediff": 0,
    "nodediffper": 0,
    "validatordiff": 0,
    "validatordiffper": 0,
    "totaldiff": 0,
    "totaldiffper": 0,
    "rank": 31,
    "created": "2022-12-11 14:02:12",
    "chaintype": "PoS"
  },
  {
    "name": "Osmosis",
    "symbol": "OSMO",
    "timestamp": "2022-12-10 18:03:53",
    "validators": 150,
    "nodes": 0,
    "total": 150,
    "source": "https://www.mintscan.io/osmosis/validators",
    "market_cap_rank": 64,
    "market_cap": 630520174,
    "volume": 83436599,
    "nodediff": 0,
    "nodediffper": 0,
    "validatordiff": 0,
    "validatordiffper": 0,
    "totaldiff": 0,
    "totaldiffper": 0,
    "rank": 32,
    "created": "2022-12-11 14:02:12",
    "chaintype": "PoS"
  },
  {
    "name": "Harmony",
    "symbol": "ONE",
    "timestamp": "2022-12-11 10:05:42",
    "validators": 147,
    "nodes": 0,
    "total": 147,
    "source": "https://staking.harmony.one/validators/mainnet",
    "market_cap_rank": 162,
    "market_cap": 176530486,
    "volume": 4779670,
    "nodediff": 0,
    "nodediffper": 0,
    "validatordiff": -1,
    "validatordiffper": -0.68,
    "totaldiff": -1,
    "totaldiffper": -0.68,
    "rank": 33,
    "created": "2022-12-11 14:02:12",
    "chaintype": "PoS"
  },
  {
    "name": "Near",
    "symbol": "NEAR",
    "timestamp": "2022-12-10 22:02:46",
    "validators": 134,
    "nodes": 0,
    "total": 134,
    "source": "https://explorer.near.org/nodes/validators",
    "market_cap_rank": 35,
    "market_cap": 1438076866,
    "volume": 36122618,
    "nodediff": 0,
    "nodediffper": 0,
    "validatordiff": 0,
    "validatordiffper": 0,
    "totaldiff": 0,
    "totaldiffper": 0,
    "rank": 34,
    "created": "2022-12-11 14:02:12",
    "chaintype": "PoS"
  },
  {
    "name": "NEM",
    "symbol": "XEM",
    "timestamp": "2022-10-05 10:06:52",
    "validators": 0,
    "nodes": 134,
    "total": 134,
    "source": "https://nemnodes.org/supernodes/",
    "market_cap_rank": 107,
    "market_cap": 376650783,
    "volume": 9219668,
    "nodediff": 0,
    "nodediffper": 0,
    "validatordiff": 0,
    "validatordiffper": 0,
    "totaldiff": 0,
    "totaldiffper": 0,
    "rank": 35,
    "created": "2022-12-11 14:02:12",
    "chaintype": "PoW"
  },
  {
    "name": "TomoChain",
    "symbol": "TOMO",
    "timestamp": "2022-12-10 22:03:08",
    "validators": 131,
    "nodes": 0,
    "total": 131,
    "source": "https://tomoscan.io/masternodes",
    "market_cap_rank": 547,
    "market_cap": 28170999,
    "volume": 2599709,
    "nodediff": 0,
    "nodediffper": 0,
    "validatordiff": -1,
    "validatordiffper": -0.76,
    "totaldiff": -1,
    "totaldiffper": -0.76,
    "rank": 36,
    "created": "2022-12-11 14:02:12",
    "chaintype": "PoS"
  },
  {
    "name": "Oasis Network",
    "symbol": "Rose",
    "timestamp": "2022-10-03 10:07:16",
    "validators": 120,
    "nodes": 0,
    "total": 120,
    "source": "https://www.oasisscan.com/validators",
    "market_cap_rank": 123,
    "market_cap": 296871206,
    "volume": 20505318,
    "nodediff": 0,
    "nodediffper": 0,
    "validatordiff": 0,
    "validatordiffper": 0,
    "totaldiff": 0,
    "totaldiffper": 0,
    "rank": 37,
    "created": "2022-12-11 14:02:12",
    "chaintype": "PoS"
  },
  {
    "name": "Pirate Chain",
    "symbol": "ARRR",
    "timestamp": "2022-12-11 10:05:30",
    "validators": 0,
    "nodes": 103,
    "total": 103,
    "source": "https://dexstats.info/",
    "market_cap_rank": 307,
    "market_cap": 68916696,
    "volume": 59526,
    "nodediff": 8,
    "nodediffper": 8.42,
    "validatordiff": 0,
    "validatordiffper": 0,
    "totaldiff": 8,
    "totaldiffper": 8.42,
    "rank": 38,
    "created": "2022-12-11 14:02:12",
    "chaintype": "PoW"
  },
  {
    "name": "VeChain",
    "symbol": "VET",
    "timestamp": "2022-11-24 10:06:00",
    "validators": 101,
    "nodes": 0,
    "total": 101,
    "source": "https://vechainstats.com/authority-nodes/",
    "market_cap_rank": 35,
    "market_cap": 1384687920,
    "volume": 48278025,
    "nodediff": 0,
    "nodediffper": 0,
    "validatordiff": 0,
    "validatordiffper": 0,
    "totaldiff": 0,
    "totaldiffper": 0,
    "rank": 39,
    "created": "2022-12-11 14:02:12",
    "chaintype": "PoS"
  },
  {
    "name": "Kava",
    "symbol": "KAVA",
    "timestamp": "2022-09-16 22:03:41",
    "validators": 100,
    "nodes": 0,
    "total": 100,
    "source": "https://atomscan.com/kava/validators",
    "market_cap_rank": 102,
    "market_cap": 396032823,
    "volume": 14434859,
    "nodediff": 0,
    "nodediffper": 0,
    "validatordiff": 0,
    "validatordiffper": 0,
    "totaldiff": 0,
    "totaldiffper": 0,
    "rank": 40,
    "created": "2022-12-11 14:02:12",
    "chaintype": "PoS"
  },
  {
    "name": "Cronos",
    "symbol": "CRO",
    "timestamp": "2022-12-11 14:02:03",
    "validators": 100,
    "nodes": 0,
    "total": 100,
    "source": "https://crypto.org/explorer/",
    "consensus_long": "Byzantine Fault Tolerant",
    "consensus_short": "BFT",
    "market_cap_rank": 32,
    "market_cap": 1613443821,
    "volume": 12400393,
    "nodediff": 0,
    "nodediffper": 0,
    "validatordiff": 0,
    "validatordiffper": 0,
    "totaldiff": 0,
    "totaldiffper": 0,
    "rank": 41,
    "created": "2022-12-11 14:02:12",
    "chaintype": "PoS"
  },
  {
    "name": "Casper",
    "symbol": "CSPR",
    "timestamp": "2022-12-11 14:02:09",
    "validators": 100,
    "nodes": 0,
    "total": 100,
    "source": "https://cspr.live/validators",
    "consensus_long": "Proof of Stake",
    "consensus_short": "PoS",
    "market_cap_rank": 103,
    "market_cap": 322659612,
    "volume": 4256504,
    "nodediff": 0,
    "nodediffper": 0,
    "validatordiff": 0,
    "validatordiffper": 0,
    "totaldiff": 0,
    "totaldiffper": 0,
    "rank": 42,
    "created": "2022-12-11 14:02:12",
    "chaintype": "PoS"
  },
  {
    "name": "Stellar",
    "symbol": "XLM",
    "timestamp": "2022-12-10 22:02:49",
    "validators": 91,
    "nodes": 0,
    "total": 91,
    "source": "https://www.stellarbeat.io/validators",
    "market_cap_rank": 28,
    "market_cap": 2201901659,
    "volume": 29642752,
    "nodediff": 0,
    "nodediffper": 0,
    "validatordiff": 3,
    "validatordiffper": 3.41,
    "totaldiff": 3,
    "totaldiffper": 3.41,
    "rank": 43,
    "created": "2022-12-11 14:02:12",
    "chaintype": "PoS"
  },
  {
    "name": "THORChain",
    "symbol": "RUNE",
    "timestamp": "2022-12-11 10:05:29",
    "validators": 88,
    "nodes": 0,
    "total": 88,
    "source": "https://thorchain.net/nodes",
    "market_cap_rank": 85,
    "market_cap": 429323808,
    "volume": 24824756,
    "nodediff": 0,
    "nodediffper": 0,
    "validatordiff": 0,
    "validatordiffper": 0,
    "totaldiff": 0,
    "totaldiffper": 0,
    "rank": 44,
    "created": "2022-12-11 14:02:12",
    "chaintype": "PoS"
  },
  {
    "name": "Polygon",
    "symbol": "MATIC",
    "timestamp": "2022-10-03 22:03:30",
    "validators": 79,
    "nodes": 0,
    "total": 79,
    "source": "https://polygonscan.com/stat/miner",
    "market_cap_rank": 14,
    "market_cap": 5952367709,
    "volume": 341223249,
    "nodediff": 0,
    "nodediffper": 0,
    "validatordiff": 1,
    "validatordiffper": 1.28,
    "totaldiff": 1,
    "totaldiffper": 1.28,
    "rank": 45,
    "created": "2022-12-11 14:02:12",
    "chaintype": "PoS"
  },
  {
    "name": "IoTeX",
    "symbol": "IOTX",
    "timestamp": "2022-10-03 22:02:57",
    "validators": 79,
    "nodes": 0,
    "total": 79,
    "source": "https://iotexscan.io/validators",
    "market_cap_rank": 133,
    "market_cap": 265316954,
    "volume": 5568398,
    "nodediff": 0,
    "nodediffper": 0,
    "validatordiff": 0,
    "validatordiffper": 0,
    "totaldiff": 0,
    "totaldiffper": 0,
    "rank": 46,
    "created": "2022-12-11 14:02:12",
    "chaintype": "PoS"
  },
  {
    "name": "Secret",
    "symbol": "SCRT",
    "timestamp": "2022-12-11 10:05:53",
    "validators": 0,
    "nodes": 75,
    "total": 75,
    "source": "https://secretnodes.com/validators",
    "market_cap_rank": 183,
    "market_cap": 150072369,
    "volume": 3632806,
    "nodediff": 0,
    "nodediffper": 0,
    "validatordiff": 0,
    "validatordiffper": 0,
    "totaldiff": 0,
    "totaldiffper": 0,
    "rank": 47,
    "created": "2022-12-11 14:02:12",
    "chaintype": "PoW"
  },
  {
    "name": "Fantom",
    "symbol": "FTM",
    "timestamp": "2022-10-04 18:11:37",
    "validators": 71,
    "nodes": 0,
    "total": 71,
    "source": "https://explorer.fantom.network/staking",
    "market_cap_rank": 74,
    "market_cap": 578029426,
    "volume": 108170138,
    "nodediff": 0,
    "nodediffper": 0,
    "validatordiff": -1,
    "validatordiffper": -1.39,
    "totaldiff": -1,
    "totaldiffper": -1.39,
    "rank": 48,
    "created": "2022-12-11 14:02:12",
    "chaintype": "PoS"
  },
  {
    "name": "DigiByte",
    "symbol": "DGB",
    "timestamp": "2022-12-11 14:01:46",
    "validators": 0,
    "nodes": 70,
    "total": 70,
    "source": "https://chainz.cryptoid.info/dgb/#!network",
    "market_cap_rank": 201,
    "market_cap": 123038376,
    "volume": 3018662,
    "nodediff": -3,
    "nodediffper": -4.11,
    "validatordiff": 0,
    "validatordiffper": 0,
    "totaldiff": -3,
    "totaldiffper": -4.11,
    "rank": 49,
    "created": "2022-12-11 14:02:12",
    "chaintype": "PoW"
  },
  {
    "name": "Moonbeam",
    "symbol": "GLMR",
    "timestamp": "2022-12-10 18:03:45",
    "validators": 68,
    "nodes": 0,
    "total": 68,
    "source": "https://moonbeam.subscan.io/validator",
    "market_cap_rank": 159,
    "market_cap": 186725664,
    "volume": 14183560,
    "nodediff": 0,
    "nodediffper": 0,
    "validatordiff": 0,
    "validatordiffper": 0,
    "totaldiff": 0,
    "totaldiffper": 0,
    "rank": 50,
    "created": "2022-12-11 14:02:12",
    "chaintype": "PoS"
  },
  {
    "name": "IOST",
    "symbol": "IOST",
    "timestamp": "2022-12-10 22:03:02",
    "validators": 63,
    "nodes": 0,
    "total": 63,
    "source": "https://www.iostabc.com/producers/",
    "market_cap_rank": 150,
    "market_cap": 203603496,
    "volume": 6615254,
    "nodediff": 0,
    "nodediffper": 0,
    "validatordiff": 0,
    "validatordiffper": 0,
    "totaldiff": 0,
    "totaldiffper": 0,
    "rank": 51,
    "created": "2022-12-11 14:02:12",
    "chaintype": "PoS"
  },
  {
    "name": "Arweave",
    "symbol": "AR",
    "timestamp": "2022-09-20 14:12:09",
    "validators": 63,
    "nodes": 0,
    "total": 63,
    "source": "https://v2.viewblock.io/arweave",
    "consensus_long": "Proof of Access",
    "consensus_short": "PoA",
    "market_cap_rank": 86,
    "market_cap": 481695974,
    "volume": 13098423,
    "nodediff": 0,
    "nodediffper": 0,
    "validatordiff": 0,
    "validatordiffper": 0,
    "totaldiff": 0,
    "totaldiffper": 0,
    "rank": 52,
    "created": "2022-12-11 14:02:12",
    "chaintype": "PoS"
  },
  {
    "name": "Komodo",
    "symbol": "KMD",
    "timestamp": "2022-12-11 10:05:55",
    "validators": 0,
    "nodes": 58,
    "total": 58,
    "source": "https://dexstats.info/",
    "market_cap_rank": 528,
    "market_cap": 29330394,
    "volume": 760065,
    "nodediff": 6,
    "nodediffper": 11.54,
    "validatordiff": 0,
    "validatordiffper": 0,
    "totaldiff": 6,
    "totaldiffper": 11.54,
    "rank": 53,
    "created": "2022-12-11 14:02:12",
    "chaintype": "PoW"
  },
  {
    "name": "Lisk",
    "symbol": "LSK",
    "timestamp": "2022-12-10 22:02:51",
    "validators": 0,
    "nodes": 57,
    "total": 57,
    "source": "https://liskscan.com/delegates",
    "market_cap_rank": 205,
    "market_cap": 120851117,
    "volume": 9174128,
    "nodediff": 0,
    "nodediffper": 0,
    "validatordiff": 0,
    "validatordiffper": 0,
    "totaldiff": 0,
    "totaldiffper": 0,
    "rank": 54,
    "created": "2022-12-11 14:02:12",
    "chaintype": "PoW"
  },
  {
    "name": "SXP",
    "symbol": "SXP",
    "timestamp": "2022-10-03 10:07:21",
    "validators": 53,
    "nodes": 0,
    "total": 53,
    "source": "https://explorer.solar.org/delegates",
    "market_cap_rank": 178,
    "market_cap": 173385137,
    "volume": 13194831,
    "nodediff": 0,
    "nodediffper": 0,
    "validatordiff": 0,
    "validatordiffper": 0,
    "totaldiff": 0,
    "totaldiffper": 0,
    "rank": 55,
    "created": "2022-12-11 14:02:12",
    "chaintype": "PoS"
  },
  {
    "name": "MediBloc",
    "symbol": "MED",
    "timestamp": "2022-12-10 22:02:55",
    "validators": 50,
    "nodes": 0,
    "total": 50,
    "source": "https://www.mintscan.io/medibloc/validators",
    "market_cap_rank": 260,
    "market_cap": 82491713,
    "volume": 593722,
    "nodediff": 0,
    "nodediffper": 0,
    "validatordiff": 0,
    "validatordiffper": 0,
    "totaldiff": 0,
    "totaldiffper": 0,
    "rank": 56,
    "created": "2022-12-11 14:02:12",
    "chaintype": "PoS"
  },
  {
    "name": "Horizen",
    "symbol": "ZEN",
    "timestamp": "2022-12-11 10:05:37",
    "validators": 0,
    "nodes": 46,
    "total": 46,
    "source": "https://explorer.horizen.io/",
    "market_cap_rank": 193,
    "market_cap": 134851131,
    "volume": 8843834,
    "nodediff": 1,
    "nodediffper": 2.22,
    "validatordiff": 0,
    "validatordiffper": 0,
    "totaldiff": 1,
    "totaldiffper": 2.22,
    "rank": 57,
    "created": "2022-12-11 14:02:12",
    "chaintype": "PoW"
  },
  {
    "name": "Helium",
    "symbol": "HNT",
    "timestamp": "2022-12-10 18:03:47",
    "validators": 43,
    "nodes": 0,
    "total": 43,
    "source": "https://api.helium.io/v1/validators/elected",
    "market_cap_rank": 113,
    "market_cap": 286491428,
    "volume": 1035084,
    "nodediff": 0,
    "nodediffper": 0,
    "validatordiff": 0,
    "validatordiffper": 0,
    "totaldiff": 0,
    "totaldiffper": 0,
    "rank": 58,
    "created": "2022-12-11 14:02:12",
    "chaintype": "PoS"
  },
  {
    "name": "Symbol",
    "symbol": "XYM",
    "timestamp": "2022-12-10 18:03:44",
    "validators": 41,
    "nodes": 0,
    "total": 41,
    "source": "https://symbol.fyi/nodes",
    "market_cap_rank": 4404,
    "market_cap": 0.0,
    "volume": 513942,
    "nodediff": 0,
    "nodediffper": 0,
    "validatordiff": 0,
    "validatordiffper": 0,
    "totaldiff": 0,
    "totaldiffper": 0,
    "rank": 59,
    "created": "2022-12-11 14:02:12",
    "chaintype": "PoS"
  },
  {
    "name": "Klaytn",
    "symbol": "Klay",
    "timestamp": "2022-10-03 22:03:39",
    "validators": 36,
    "nodes": 0,
    "total": 36,
    "source": "https://scope.klaytn.com/gcinfo/council",
    "market_cap_rank": 72,
    "market_cap": 579325891,
    "volume": 16218032,
    "nodediff": 0,
    "nodediffper": 0,
    "validatordiff": 0,
    "validatordiffper": 0,
    "totaldiff": 0,
    "totaldiffper": 0,
    "rank": 60,
    "created": "2022-12-11 14:02:12",
    "chaintype": "PoS"
  },
  {
    "name": "Tron",
    "symbol": "TRX",
    "timestamp": "2022-12-11 10:05:31",
    "validators": 27,
    "nodes": 0,
    "total": 27,
    "source": "https://tronscan.org/#/sr/representatives",
    "market_cap_rank": 17,
    "market_cap": 5040993910,
    "volume": 167875167,
    "nodediff": 0,
    "nodediffper": 0,
    "validatordiff": 0,
    "validatordiffper": 0,
    "totaldiff": 0,
    "totaldiffper": 0,
    "rank": 61,
    "created": "2022-12-11 14:02:12",
    "chaintype": "PoS"
  },
  {
    "name": "Hedera",
    "symbol": "HBAR",
    "timestamp": "2022-10-04 18:15:44",
    "validators": 26,
    "nodes": 0,
    "total": 26,
    "source": "https://hashscan.io/#/mainnet/nodes",
    "market_cap_rank": 41,
    "market_cap": 1419602883,
    "volume": 31613744,
    "nodediff": 0,
    "nodediffper": 0,
    "validatordiff": 0,
    "validatordiffper": 0,
    "totaldiff": 0,
    "totaldiffper": 0,
    "rank": 62,
    "created": "2022-12-11 14:02:12",
    "chaintype": "PoS"
  },
  {
    "name": "ICON",
    "symbol": "ICX",
    "timestamp": "2022-10-04 18:11:24",
    "validators": 25,
    "nodes": 0,
    "total": 25,
    "source": "https://tracker.icon.community/governance",
    "market_cap_rank": 157,
    "market_cap": 214366422,
    "volume": 2961252,
    "nodediff": 0,
    "nodediffper": 0,
    "validatordiff": 0,
    "validatordiffper": 0,
    "totaldiff": 0,
    "totaldiffper": 0,
    "rank": 63,
    "created": "2022-12-11 14:02:12",
    "chaintype": "PoS"
  },
  {
    "name": "Hive",
    "symbol": "HIVE",
    "timestamp": "2022-12-10 18:03:38",
    "validators": 21,
    "nodes": 0,
    "total": 21,
    "source": "https://hiveblocks.com/witnesses",
    "market_cap_rank": 195,
    "market_cap": 134109587,
    "volume": 2510202,
    "nodediff": 0,
    "nodediffper": 0,
    "validatordiff": 0,
    "validatordiffper": 0,
    "totaldiff": 0,
    "totaldiffper": 0,
    "rank": 64,
    "created": "2022-12-11 14:02:12",
    "chaintype": "PoS"
  },
  {
    "name": "WAX",
    "symbol": "WAXP",
    "timestamp": "2022-12-10 22:03:04",
    "validators": 21,
    "nodes": 0,
    "total": 21,
    "source": "https://wax.bloks.io/vote",
    "market_cap_rank": 194,
    "market_cap": 137342122,
    "volume": 24667319,
    "nodediff": 0,
    "nodediffper": 0,
    "validatordiff": 0,
    "validatordiffper": 0,
    "totaldiff": 0,
    "totaldiffper": 0,
    "rank": 65,
    "created": "2022-12-11 14:02:12",
    "chaintype": "PoS"
  },
  {
    "name": "Multichain",
    "symbol": "MULTI",
    "timestamp": "2022-12-10 22:03:04",
    "validators": 0,
    "nodes": 21,
    "total": 21,
    "source": "https://anyswap.net/network",
    "market_cap_rank": 284,
    "market_cap": 75110598,
    "volume": 3640067,
    "nodediff": 0,
    "nodediffper": 0,
    "validatordiff": 0,
    "validatordiffper": 0,
    "totaldiff": 0,
    "totaldiffper": 0,
    "rank": 66,
    "created": "2022-12-11 14:02:12",
    "chaintype": "PoW"
  },
  {
    "name": "EOS",
    "symbol": "EOS",
    "timestamp": "2022-12-11 14:01:45",
    "validators": 21,
    "nodes": 0,
    "total": 21,
    "source": "https://eosauthority.com",
    "market_cap_rank": 39,
    "market_cap": 1131774125,
    "volume": 91259682,
    "nodediff": 0,
    "nodediffper": 0,
    "validatordiff": 0,
    "validatordiffper": 0,
    "totaldiff": 0,
    "totaldiffper": 0,
    "rank": 67,
    "created": "2022-12-11 14:02:12",
    "chaintype": "PoS"
  },
  {
    "name": "Bitcoin SV",
    "symbol": "BSV",
    "timestamp": "2022-12-11 14:02:11",
    "validators": 0,
    "nodes": 20,
    "total": 20,
    "source": "https://blockchair.com/bitcoin-sv/nodes",
    "consensus_long": "Proof of Work",
    "consensus_short": "PoW",
    "market_cap_rank": 51,
    "market_cap": 841595889,
    "volume": 12296456,
    "nodediff": 0,
    "nodediffper": 0,
    "validatordiff": 0,
    "validatordiffper": 0,
    "totaldiff": 0,
    "totaldiffper": 0,
    "rank": 68,
    "created": "2022-12-11 14:02:12",
    "chaintype": "PoW"
  },
  {
    "name": "GoChain",
    "symbol": "GO",
    "timestamp": "2022-12-11 14:01:56",
    "validators": 19,
    "nodes": 0,
    "total": 19,
    "source": "https://explorer.gochain.io/signers?signers_tab=daily",
    "market_cap_rank": 930,
    "market_cap": 7714375,
    "volume": 168766,
    "nodediff": 0,
    "nodediffper": 0,
    "validatordiff": 0,
    "validatordiffper": 0,
    "totaldiff": 0,
    "totaldiffper": 0,
    "rank": 69,
    "created": "2022-12-11 14:02:12",
    "chaintype": "PoS"
  },
  {
    "name": "DASH",
    "symbol": "DASH",
    "timestamp": "2022-12-11 14:01:58",
    "validators": 0,
    "nodes": 17,
    "total": 17,
    "source": "https://explorer.dash.org/",
    "market_cap_rank": 75,
    "market_cap": 518538497,
    "volume": 53145021,
    "nodediff": 1,
    "nodediffper": 6.25,
    "validatordiff": 0,
    "validatordiffper": 0,
    "totaldiff": 1,
    "totaldiffper": 6.25,
    "rank": 70,
    "created": "2022-12-11 14:02:12",
    "chaintype": "PoW"
  },
  {
    "name": "Decred",
    "symbol": "DCR",
    "timestamp": "2022-12-11 14:01:50",
    "validators": 0,
    "nodes": 16,
    "total": 16,
    "source": "https://dcrstats.com/map",
    "market_cap_rank": 104,
    "market_cap": 313639926,
    "volume": 2683703,
    "nodediff": 0,
    "nodediffper": 0,
    "validatordiff": 0,
    "validatordiffper": 0,
    "totaldiff": 0,
    "totaldiffper": 0,
    "rank": 71,
    "created": "2022-12-11 14:02:12",
    "chaintype": "PoW"
  },
  {
    "name": "Flux",
    "symbol": "FLUX",
    "timestamp": "2022-12-10 18:03:48",
    "validators": 0,
    "nodes": 16,
    "total": 16,
    "source": "https://explorer.runonflux.io/network",
    "market_cap_rank": 185,
    "market_cap": 147068441,
    "volume": 2524403,
    "nodediff": 0,
    "nodediffper": 0,
    "validatordiff": 0,
    "validatordiffper": 0,
    "totaldiff": 0,
    "totaldiffper": 0,
    "rank": 72,
    "created": "2022-12-11 14:02:12",
    "chaintype": "PoW"
  },
  {
    "name": "Ontology",
    "symbol": "ONT",
    "timestamp": "2022-12-11 10:05:44",
    "validators": 0,
    "nodes": 15,
    "total": 15,
    "source": "https://node.ont.io/",
    "market_cap_rank": 175,
    "market_cap": 163612860,
    "volume": 15154977,
    "nodediff": 0,
    "nodediffper": 0,
    "validatordiff": 0,
    "validatordiffper": 0,
    "totaldiff": 0,
    "totaldiffper": 0,
    "rank": 73,
    "created": "2022-12-11 14:02:12",
    "chaintype": "PoW"
  },
  {
    "name": "Gnosis",
    "symbol": "GNO",
    "timestamp": "2022-10-04 18:16:50",
    "validators": 13,
    "nodes": 0,
    "total": 13,
    "source": "https://gnosisscan.io/stat/miner",
    "market_cap_rank": 120,
    "market_cap": 313537817,
    "volume": 1312797,
    "nodediff": 0,
    "nodediffper": 0,
    "validatordiff": 0,
    "validatordiffper": 0,
    "totaldiff": 0,
    "totaldiffper": 0,
    "rank": 74,
    "created": "2022-12-11 14:02:12",
    "chaintype": "PoS"
  },
  {
    "name": "Bitcoin Gold",
    "symbol": "BTG",
    "timestamp": "2022-12-11 14:02:04",
    "validators": 0,
    "nodes": 12,
    "total": 12,
    "source": "https://explorer.bitcoingold.org/insight/status",
    "consensus_long": "Proof of Work",
    "consensus_short": "PoW",
    "market_cap_rank": 121,
    "market_cap": 266716260,
    "volume": 3736029,
    "nodediff": 1,
    "nodediffper": 9.09,
    "validatordiff": 0,
    "validatordiffper": 0,
    "totaldiff": 1,
    "totaldiffper": 9.09,
    "rank": 75,
    "created": "2022-12-11 14:02:12",
    "chaintype": "PoW"
  },
  {
    "name": "BitTorrent",
    "symbol": "BTT",
    "timestamp": "2022-10-04 14:21:36",
    "validators": 12,
    "nodes": 0,
    "total": 12,
    "source": "https://bttcscan.com/validators",
    "consensus_long": "Delegated Proof of Stake",
    "consensus_short": "DPoS",
    "market_cap_rank": 63,
    "market_cap": 739866920,
    "volume": 19344479,
    "nodediff": 0,
    "nodediffper": 0,
    "validatordiff": 0,
    "validatordiffper": 0,
    "totaldiff": 0,
    "totaldiffper": 0,
    "rank": 76,
    "created": "2022-12-11 14:02:12",
    "chaintype": "PoS"
  },
  {
    "name": "KuCoin",
    "symbol": "KCS",
    "timestamp": "2022-12-10 22:02:48",
    "validators": 11,
    "nodes": 0,
    "total": 11,
    "source": "https://explorer.kcc.io/en/validator",
    "market_cap_rank": 60,
    "market_cap": 646631750,
    "volume": 870397,
    "nodediff": 0,
    "nodediffper": 0,
    "validatordiff": 0,
    "validatordiffper": 0,
    "totaldiff": 0,
    "totaldiffper": 0,
    "rank": 77,
    "created": "2022-12-11 14:02:12",
    "chaintype": "PoS"
  },
  {
    "name": "NEO",
    "symbol": "NEO",
    "timestamp": "2022-12-11 10:05:41",
    "validators": 0,
    "nodes": 9,
    "total": 9,
    "source": "https://dora.coz.io/monitor",
    "market_cap_rank": 76,
    "market_cap": 507530839,
    "volume": 26907663,
    "nodediff": 0,
    "nodediffper": 0,
    "validatordiff": 0,
    "validatordiffper": 0,
    "totaldiff": 0,
    "totaldiffper": 0,
    "rank": 78,
    "created": "2022-12-11 14:02:12",
    "chaintype": "PoW"
  },
  {
    "name": "Siacoin",
    "symbol": "SC",
    "timestamp": "2022-12-11 10:05:33",
    "validators": 8,
    "nodes": 0,
    "total": 8,
    "source": "https://siastats.info/status",
    "market_cap_rank": 191,
    "market_cap": 136536511,
    "volume": 4050166,
    "nodediff": 0,
    "nodediffper": 0,
    "validatordiff": 0,
    "validatordiffper": 0,
    "totaldiff": 0,
    "totaldiffper": 0,
    "rank": 79,
    "created": "2022-12-11 14:02:12",
    "chaintype": "PoS"
  },
  {
    "name": "BNB",
    "symbol": "BNB",
    "timestamp": "2022-12-11 14:02:12",
    "validators": 0,
    "nodes": 0,
    "total": 0,
    "source": "https://www.bnbchain.org/en/staking",
    "consensus_long": "Proof of Staked Authority",
    "consensus_short": "PoSA",
    "market_cap_rank": 4,
    "market_cap": 47276717434,
    "volume": 416671370,
    "nodediff": 0,
    "nodediffper": 0,
    "validatordiff": 0,
    "validatordiffper": 0,
    "totaldiff": 0,
    "totaldiffper": 0,
    "rank": 80,
    "created": "2022-12-11 14:02:12",
    "chaintype": "PoS"
  },
  {
    "name": "Cardano",
    "symbol": "ADA",
    "timestamp": "2022-12-10 18:03:47",
    "validators": 0,
    "nodes": 0,
    "total": 0,
    "source": "https://adapools.org/",
    "market_cap_rank": 9,
    "market_cap": 10984147098,
    "volume": 116052596,
    "nodediff": 0,
    "nodediffper": 0,
    "validatordiff": 0,
    "validatordiffper": 0,
    "totaldiff": 0,
    "totaldiffper": 0,
    "rank": 81,
    "created": "2022-12-11 14:02:12",
    "chaintype": "PoS"
  }
]