[
  {
    "name": "Cosmos",
    "symbol": "ATOM",
    "timestamp": "2022-11-12 14:02:15",
    "validators": 175,
    "nodes": 0,
    "total": 175,
    "source": "https://www.mintscan.io/cosmos/validators",
    "consensus_long": "Byzantine Fault Tolerant",
    "consensus_short": "BFT",
    "market_cap_rank": 23,
    "market_cap": 3240499889,
    "volume": 244065683,
    "nodediff": 0,
    "nodediffper": 0,
    "validatordiff": 0,
    "validatordiffper": 0,
    "totaldiff": 0,
    "totaldiffper": 0
  }
]