[{"name": "Siacoin", "symbol": "SC", "timestamp": "2022-08-31 10:06:00", "validators": 8, "nodes": 0, "total": 8, "source": "https://siastats.info/status", "market_cap_rank": 161, "market_cap": 210777972, "volume": 4708086, "nodediff": 0, "nodediffper": 0, "validatordiff": 0, "validatordiffper": 0, "totaldiff": 0, "totaldiffper": 0, "rank": 1, "created": "2022-08-31 22:03:52", "chaintype": "PoS"}, {"name": "KuCoin", "symbol": "KCS", "timestamp": "2022-08-31 22:03:08", "validators": 11, "nodes": 0, "total": 11, "source": "https://explorer.kcc.io/en/validator", "market_cap_rank": 56, "market_cap": 883519980, "volume": 2361687, "nodediff": 0, "nodediffper": 0, "validatordiff": 0, "validatordiffper": 0, "totaldiff": 0, "totaldiffper": 0, "rank": 2, "created": "2022-08-31 22:03:52", "chaintype": "PoS"}, {"name": "BitTorrent", "symbol": "BTT", "timestamp": "2022-08-31 14:03:32", "validators": 12, "nodes": 0, "total": 12, "source": "https://bttcscan.com/validators", "market_cap_rank": 58, "market_cap": 841332103, "volume": 30018900, "nodediff": 0, "nodediffper": 0, "validatordiff": 0, "validatordiffper": 0, "totaldiff": 0, "totaldiffper": 0, "rank": 3, "created": "2022-08-31 22:03:52", "chaintype": "PoS"}, {"name": "EOS", "symbol": "EOS", "timestamp": "2022-08-31 14:03:18", "validators": 21, "nodes": 0, "total": 21, "source": "https://eosauthority.com", "market_cap_rank": 43, "market_cap": 1426471628, "volume": 334672541, "nodediff": 0, "nodediffper": 0, "validatordiff": 0, "validatordiffper": 0, "totaldiff": 0, "totaldiffper": 0, "rank": 4, "created": "2022-08-31 22:03:52", "chaintype": "PoS"}, {"name": "Hive", "symbol": "HIVE", "timestamp": "2022-08-31 18:05:17", "validators": 21, "nodes": 0, "total": 21, "source": "https://hiveblocks.com/witnesses", "market_cap_rank": 163, "market_cap": 208193285, "volume": 7354524, "nodediff": 0, "nodediffper": 0, "validatordiff": 0, "validatordiffper": 0, "totaldiff": 0, "totaldiffper": 0, "rank": 5, "created": "2022-08-31 22:03:52", "chaintype": "PoS"}]