[
  {
    "name": "Bitcoin",
    "symbol": "BTC",
    "timestamp": "2022-11-23 13:54:22",
    "validators": 0,
    "nodes": 15258,
    "total": 15258,
    "source": "https://bitnodes.io",
    "consensus_long": "Proof of Work",
    "consensus_short": "PoW",
    "retrieved": "2022-11-23 14:01:57",
    "market_cap_rank": 1,
    "market_cap": 316680164160,
    "volume": 26256281208,
    "nodediff": 2296,
    "nodediffper": 17.71,
    "validatordiff": 0,
    "validatordiffper": 0,
    "totaldiff": 2296,
    "totaldiffper": 17.71
  }
]