[
  {
    "name": "Bitcoin Gold",
    "symbol": "BTG",
    "timestamp": "2022-10-03 14:16:33",
    "validators": 0,
    "nodes": 13,
    "total": 13,
    "source": "https://explorer.bitcoingold.org/insight/status",
    "consensus_long": "Proof of Work",
    "consensus_short": "PoW",
    "market_cap_rank": 112,
    "market_cap": 350999194,
    "volume": 1765914,
    "nodediff": 2,
    "nodediffper": 18.18,
    "validatordiff": 0,
    "validatordiffper": 0,
    "totaldiff": 2,
    "totaldiffper": 18.18
  }
]