[{"name": "Bitcoin", "symbol": "BTC", "timestamp": "2022-12-30 14:00:27", "validators": 0, "nodes": 13393, "total": 13393, "source": "https://bitnodes.io", "consensus_long": "Proof of Work", "consensus_short": "PoW", "retrieved": "2022-12-30 14:02:12", "market_cap_rank": 1, "market_cap": 316964540157, "volume": 15304222151, "nodediff": -1805, "nodediffper": -11.88, "validatordiff": 0, "validatordiffper": 0, "totaldiff": -1805, "totaldiffper": -11.88, "rank": 1, "created": "2022-12-30 22:02:57", "chaintype": "PoW"}, {"name": "Ethereum", "symbol": "ETH", "timestamp": "2022-12-30 18:04:10", "validators": 493484, "nodes": 8120, "total": 501604, "source": "https://beaconcha.in", "market_cap_rank": 2, "market_cap": 144026905407, "volume": 4149611860, "nodediff": 0, "nodediffper": 0, "validatordiff": 404, "validatordiffper": 0.08, "totaldiff": 404, "totaldiffper": 0.08, "rank": 2, "created": "2022-12-30 22:02:57", "chaintype": "PoS"}, {"name": "Zcash", "symbol": "ZEC", "timestamp": "2022-12-30 10:05:45", "validators": 0, "nodes": 7874, "total": 7874, "source": "https://blockchair.com/zcash/nodes", "market_cap_rank": 66, "market_cap": 489560782, "volume": 29260107, "nodediff": 63, "nodediffper": 0.81, "validatordiff": 0, "validatordiffper": 0, "totaldiff": 63, "totaldiffper": 0.81, "rank": 3, "created": "2022-12-30 22:02:57", "chaintype": "PoW"}, {"name": "Filecoin", "symbol": "FIL", "timestamp": "2022-10-04 18:16:55", "validators": 0, "nodes": 4049, "total": 4049, "source": "https://filfox.info/en", "market_cap_rank": 38, "market_cap": 1638580071, "volume": 95428368, "nodediff": 7, "nodediffper": 0.17, "validatordiff": 0, "validatordiffper": 0, "totaldiff": 7, "totaldiffper": 0.17, "rank": 4, "created": "2022-12-30 22:02:57", "chaintype": "PoW"}, {"name": "Zilliqa", "symbol": "ZIL", "timestamp": "2022-09-16 10:05:49", "validators": 0, "nodes": 2400, "total": 2400, "source": "https://viewblock.io/zilliqa", "market_cap_rank": 85, "market_cap": 502689681, "volume": 34320901, "nodediff": 0, "nodediffper": 0, "validatordiff": -21, "validatordiffper": -100.0, "totaldiff": -21, "totaldiffper": -0.87, "rank": 5, "created": "2022-12-30 22:02:57", "chaintype": "PoW"}]