[{"name": "Bitcoin", "symbol": "BTC", "timestamp": "2022-12-15 13:57:02", "validators": 0, "nodes": 12954, "total": 12954, "source": "https://bitnodes.io", "consensus_long": "Proof of Work", "consensus_short": "PoW", "retrieved": "2022-12-15 14:03:21", "market_cap_rank": 1, "market_cap": 335997601658, "volume": 28131920935, "nodediff": -1478, "nodediffper": -10.24, "validatordiff": 0, "validatordiffper": 0, "totaldiff": -1478, "totaldiffper": -10.24, "rank": 1, "created": "2022-12-16 10:05:59", "chaintype": "PoW"}, {"name": "IOTA", "symbol": "MIOTA", "timestamp": "2022-10-03 22:04:00", "validators": 0, "nodes": 357, "total": 357, "source": "https://thetangle.org/nodes", "market_cap_rank": 60, "market_cap": 772554256, "volume": 13075791, "nodediff": -5, "nodediffper": -1.38, "validatordiff": 0, "validatordiffper": 0, "totaldiff": -5, "totaldiffper": -1.38, "rank": 2, "created": "2022-12-16 10:05:59", "chaintype": "PoW"}, {"name": "Ripple", "symbol": "XRP", "timestamp": "2022-12-15 18:03:57", "validators": 116, "nodes": 683, "total": 799, "source": "https://livenet.xrpl.org/", "market_cap_rank": 6, "market_cap": 19232620820, "volume": 972619893, "nodediff": -1, "nodediffper": -0.15, "validatordiff": -1, "validatordiffper": -0.85, "totaldiff": -2, "totaldiffper": -0.25, "rank": 3, "created": "2022-12-16 10:05:59", "chaintype": "PoS"}]