[{"name": "Lisk", "symbol": "LSK", "timestamp": "2022-10-13 22:03:04", "validators": 0, "nodes": 54, "total": 54, "source": "https://liskscan.com/delegates", "market_cap_rank": 203, "market_cap": 132515115, "volume": 3844441, "nodediff": -4, "nodediffper": -6.9, "validatordiff": 0, "validatordiffper": 0, "totaldiff": -4, "totaldiffper": -6.9, "rank": 1, "created": "2022-10-14 10:06:56", "chaintype": "PoW"}, {"name": "Pirate Chain", "symbol": "ARRR", "timestamp": "2022-10-14 10:06:46", "validators": 0, "nodes": 127, "total": 127, "source": "https://dexstats.info/", "market_cap_rank": 301, "market_cap": 74780460, "volume": 149825, "nodediff": -6, "nodediffper": -4.51, "validatordiff": 0, "validatordiffper": 0, "totaldiff": -6, "totaldiffper": -4.51, "rank": 2, "created": "2022-10-14 10:06:56", "chaintype": "PoW"}, {"name": "Bitcoin", "symbol": "BTC", "timestamp": "2022-10-13 14:07:25", "validators": 0, "nodes": 15069, "total": 15069, "source": "https://bitnodes.io", "consensus_long": "Proof of Work", "consensus_short": "PoW", "retrieved": "2022-10-13 14:09:07", "market_cap_rank": 1, "market_cap": 364562508181, "volume": 22451976089, "nodediff": -286, "nodediffper": -1.86, "validatordiff": 0, "validatordiffper": 0, "totaldiff": -286, "totaldiffper": -1.86, "rank": 3, "created": "2022-10-14 10:06:56", "chaintype": "PoW"}, {"name": "IOTA", "symbol": "MIOTA", "timestamp": "2022-10-03 22:04:00", "validators": 0, "nodes": 357, "total": 357, "source": "https://thetangle.org/nodes", "market_cap_rank": 60, "market_cap": 772554256, "volume": 13075791, "nodediff": -5, "nodediffper": -1.38, "validatordiff": 0, "validatordiffper": 0, "totaldiff": -5, "totaldiffper": -1.38, "rank": 4, "created": "2022-10-14 10:06:56", "chaintype": "PoW"}, {"name": "Dogecoin", "symbol": "DOGE", "timestamp": "2022-10-13 14:09:36", "validators": 0, "nodes": 907, "total": 907, "source": "https://blockchair.com/en/dogecoin/nodes", "market_cap_rank": 10, "market_cap": 7861569168, "volume": 228410215, "nodediff": -4, "nodediffper": -0.44, "validatordiff": 0, "validatordiffper": 0, "totaldiff": -4, "totaldiffper": -0.44, "rank": 5, "created": "2022-10-14 10:06:56", "chaintype": "PoW"}]