[{"name": "Horizen", "symbol": "ZEN", "timestamp": "2022-10-05 10:06:20", "validators": 0, "nodes": 8, "total": 8, "source": "https://explorer.horizen.io/", "market_cap_rank": 172, "market_cap": 181363011, "volume": 5494304, "nodediff": -41, "nodediffper": -83.67, "validatordiff": 0, "validatordiffper": 0, "totaldiff": -41, "totaldiffper": -83.67, "rank": 1, "created": "2022-10-05 22:03:15", "chaintype": "PoW"}, {"name": "DigiByte", "symbol": "DGB", "timestamp": "2022-10-05 14:26:03", "validators": 0, "nodes": 17, "total": 17, "source": "https://chainz.cryptoid.info/dgb/#!network", "market_cap_rank": 196, "market_cap": 149561020, "volume": 1942566, "nodediff": -72, "nodediffper": -80.9, "validatordiff": 0, "validatordiffper": 0, "totaldiff": -72, "totaldiffper": -80.9, "rank": 2, "created": "2022-10-05 22:03:15", "chaintype": "PoW"}, {"name": "Lisk", "symbol": "LSK", "timestamp": "2022-10-05 22:03:10", "validators": 0, "nodes": 37, "total": 37, "source": "https://liskscan.com/delegates", "market_cap_rank": 201, "market_cap": 139940160, "volume": 2085619, "nodediff": -18, "nodediffper": -32.73, "validatordiff": 0, "validatordiffper": 0, "totaldiff": -18, "totaldiffper": -32.73, "rank": 3, "created": "2022-10-05 22:03:15", "chaintype": "PoW"}, {"name": "DASH", "symbol": "DASH", "timestamp": "2022-10-05 14:26:27", "validators": 0, "nodes": 17, "total": 17, "source": "https://explorer.dash.org/", "market_cap_rank": 87, "market_cap": 457490204, "volume": 48061062, "nodediff": -5, "nodediffper": -22.73, "validatordiff": 0, "validatordiffper": 0, "totaldiff": -5, "totaldiffper": -22.73, "rank": 4, "created": "2022-10-05 22:03:15", "chaintype": "PoW"}, {"name": "Bitcoin Gold", "symbol": "BTG", "timestamp": "2022-10-05 14:26:32", "validators": 0, "nodes": 12, "total": 12, "source": "https://explorer.bitcoingold.org/insight/status", "consensus_long": "Proof of Work", "consensus_short": "PoW", "market_cap_rank": 113, "market_cap": 357039347, "volume": 2957311, "nodediff": -1, "nodediffper": -7.69, "validatordiff": 0, "validatordiffper": 0, "totaldiff": -1, "totaldiffper": -7.69, "rank": 5, "created": "2022-10-05 22:03:15", "chaintype": "PoW"}]