[{"name": "Horizen", "symbol": "ZEN", "timestamp": "2022-10-19 10:09:50", "validators": 0, "nodes": 8, "total": 8, "source": "https://explorer.horizen.io/", "market_cap_rank": 186, "market_cap": 163723304, "volume": 5572528, "nodediff": -20, "nodediffper": -71.43, "validatordiff": 0, "validatordiffper": 0, "totaldiff": -20, "totaldiffper": -71.43, "rank": 1, "created": "2022-10-19 22:03:00", "chaintype": "PoW"}, {"name": "Bitcoin Gold", "symbol": "BTG", "timestamp": "2022-10-19 14:14:26", "validators": 0, "nodes": 11, "total": 11, "source": "https://explorer.bitcoingold.org/insight/status", "consensus_long": "Proof of Work", "consensus_short": "PoW", "market_cap_rank": 123, "market_cap": 303640928, "volume": 4745420, "nodediff": -1, "nodediffper": -8.33, "validatordiff": 0, "validatordiffper": 0, "totaldiff": -1, "totaldiffper": -8.33, "rank": 2, "created": "2022-10-19 22:03:00", "chaintype": "PoW"}, {"name": "IOTA", "symbol": "MIOTA", "timestamp": "2022-10-03 22:04:00", "validators": 0, "nodes": 357, "total": 357, "source": "https://thetangle.org/nodes", "market_cap_rank": 60, "market_cap": 772554256, "volume": 13075791, "nodediff": -5, "nodediffper": -1.38, "validatordiff": 0, "validatordiffper": 0, "totaldiff": -5, "totaldiffper": -1.38, "rank": 3, "created": "2022-10-19 22:03:00", "chaintype": "PoW"}, {"name": "Bitcoin Cash", "symbol": "BCH", "timestamp": "2022-10-19 14:14:06", "validators": 0, "nodes": 767, "total": 767, "source": "https://cashnodes.io/", "consensus_long": "Proof of Work", "consensus_short": "PoW", "market_cap_rank": 33, "market_cap": 2061587100, "volume": 465771493, "nodediff": -4, "nodediffper": -0.52, "validatordiff": 0, "validatordiffper": 0, "totaldiff": -4, "totaldiffper": -0.52, "rank": 4, "created": "2022-10-19 22:03:00", "chaintype": "PoW"}, {"name": "Dogecoin", "symbol": "DOGE", "timestamp": "2022-10-19 14:14:25", "validators": 0, "nodes": 899, "total": 899, "source": "https://blockchair.com/en/dogecoin/nodes", "market_cap_rank": 10, "market_cap": 8032426412, "volume": 250663683, "nodediff": -4, "nodediffper": -0.44, "validatordiff": 0, "validatordiffper": 0, "totaldiff": -4, "totaldiffper": -0.44, "rank": 5, "created": "2022-10-19 22:03:00", "chaintype": "PoW"}]