[
    {
        "validatorName": "Coinbase Cloud",
        "validatorVotingPower": 9156776.36,
        "validatorVotingPowerProportion": 2.52,
        "rank": 1
    },
    {
        "validatorName": "Staking Facilities",
        "validatorVotingPower": 8720243.28,
        "validatorVotingPowerProportion": 2.4,
        "rank": 2
    },
    {
        "validatorName": "binance staking",
        "validatorVotingPower": 6274324.74,
        "validatorVotingPowerProportion": 1.72,
        "rank": 3
    },
    {
        "validatorName": "SOL Community",
        "validatorVotingPower": 5268070.97,
        "validatorVotingPowerProportion": 1.45,
        "rank": 4
    },
    {
        "validatorName": "Everstake",
        "validatorVotingPower": 4928938.45,
        "validatorVotingPowerProportion": 1.35,
        "rank": 5
    },
    {
        "validatorName": "a16z",
        "validatorVotingPower": 4748429.97,
        "validatorVotingPowerProportion": 1.3,
        "rank": 6
    }
]