[
  {
    "hosting_provider": "TeraSwitch",
    "count": 88,
    "validatorVotingPower": 67588909.67,
    "validatorVotingPowerProportion": 18.22
  },
  {
    "hosting_provider": "OVHcloud",
    "count": 614,
    "validatorVotingPower": 50260236.74999997,
    "validatorVotingPowerProportion": 13.55
  },
  {
    "hosting_provider": "Amazon.com",
    "count": 36,
    "validatorVotingPower": 46754412.199999996,
    "validatorVotingPowerProportion": 12.6
  },
  {
    "hosting_provider": "Equinix Metal",
    "count": 65,
    "validatorVotingPower": 39292920.269999966,
    "validatorVotingPowerProportion": 10.59
  },
  {
    "hosting_provider": "Cherry Servers",
    "count": 24,
    "validatorVotingPower": 14433628.420000004,
    "validatorVotingPowerProportion": 3.89
  },
  {
    "hosting_provider": "Others",
    "count": 1048,
    "validatorVotingPower": 152672775.58000007,
    "validatorVotingPowerProportion": 41.151371760436334
  }
]