[
  {
    "asn": 54825,
    "count": 90,
    "validatorVotingPower": 90285869.04000002,
    "hosting_provider": "Equinix Metal",
    "timestamp": 1667991977
  },
  {
    "asn": 16509,
    "count": 36,
    "validatorVotingPower": 58640992.36,
    "hosting_provider": "Amazon.com",
    "timestamp": 1667991977
  },
  {
    "asn": 20326,
    "count": 68,
    "validatorVotingPower": 50497880.25000001,
    "hosting_provider": "TeraSwitch",
    "timestamp": 1667991977
  },
  {
    "asn": 16276,
    "count": 617,
    "validatorVotingPower": 42472985.219999984,
    "hosting_provider": "OVHcloud",
    "timestamp": 1667991977
  },
  {
    "asn": 0,
    "count": 38,
    "validatorVotingPower": 17539105.289999995,
    "hosting_provider": "Unknown",
    "timestamp": 1667991977
  },
  {
    "asn": 24940,
    "count": 83,
    "validatorVotingPower": 13224426.359999994,
    "hosting_provider": "Hetzner Online",
    "timestamp": 1667991977
  },
  {
    "asn": 18450,
    "count": 132,
    "validatorVotingPower": 10552253.7,
    "hosting_provider": "WebNX",
    "timestamp": 1667991977
  },
  {
    "asn": 199610,
    "count": 4,
    "validatorVotingPower": 10333882.750000002,
    "hosting_provider": "Nitrado (marbis)",
    "timestamp": 1667991977
  },
  {
    "asn": 23470,
    "count": 97,
    "validatorVotingPower": 10224126.389999995,
    "hosting_provider": "ReliableSite.Net",
    "timestamp": 1667991977
  },
  {
    "asn": 15598,
    "count": 2,
    "validatorVotingPower": 8726083.709999999,
    "hosting_provider": "IP Exchange",
    "timestamp": 1667991977
  },
  {
    "asn": 14618,
    "count": 4,
    "validatorVotingPower": 7244184.0,
    "hosting_provider": "Amazon AES",
    "timestamp": 1667991977
  },
  {
    "asn": 7979,
    "count": 3,
    "validatorVotingPower": 6338994.79,
    "hosting_provider": "SERVERS.COM",
    "timestamp": 1667991977
  },
  {
    "asn": 19318,
    "count": 91,
    "validatorVotingPower": 6208363.16,
    "hosting_provider": "InterServer",
    "timestamp": 1667991977
  },
  {
    "asn": 396356,
    "count": 9,
    "validatorVotingPower": 6178706.090000001,
    "hosting_provider": "Latitude.sh_AS396356",
    "timestamp": 1667991977
  },
  {
    "asn": 16125,
    "count": 14,
    "validatorVotingPower": 5444669.02,
    "hosting_provider": "Cherry Servers",
    "timestamp": 1667991977
  },
  {
    "asn": 6939,
    "count": 2,
    "validatorVotingPower": 4544180.38,
    "hosting_provider": "Hurricane Electric",
    "timestamp": 1667991977
  },
  {
    "asn": 29802,
    "count": 61,
    "validatorVotingPower": 4294138.94,
    "hosting_provider": "Hivelocity INC",
    "timestamp": 1667991977
  },
  {
    "asn": 201814,
    "count": 62,
    "validatorVotingPower": 3349191.979999999,
    "hosting_provider": "Mevspace",
    "timestamp": 1667991977
  },
  {
    "asn": 49981,
    "count": 55,
    "validatorVotingPower": 3100832.52,
    "hosting_provider": "Worldstream BV",
    "timestamp": 1667991977
  },
  {
    "asn": 25248,
    "count": 2,
    "validatorVotingPower": 2761395.92,
    "hosting_provider": "Radiokomunikace",
    "timestamp": 1667991977
  },
  {
    "asn": 21409,
    "count": 37,
    "validatorVotingPower": 2324194.7600000002,
    "hosting_provider": "Ikoula",
    "timestamp": 1667991977
  },
  {
    "asn": 24961,
    "count": 29,
    "validatorVotingPower": 1872093.9800000002,
    "hosting_provider": "myLoc managed IT AG",
    "timestamp": 1667991977
  },
  {
    "asn": 31898,
    "count": 8,
    "validatorVotingPower": 1826657.4699999997,
    "hosting_provider": "Oracle Cloud Infrastructure",
    "timestamp": 1667991977
  },
  {
    "asn": 51945,
    "count": 1,
    "validatorVotingPower": 1651574.1,
    "hosting_provider": "ConnetU Ltd",
    "timestamp": 1667991977
  },
  {
    "asn": 9009,
    "count": 6,
    "validatorVotingPower": 1404170.03,
    "hosting_provider": "M247",
    "timestamp": 1667991977
  },
  {
    "asn": 60945,
    "count": 2,
    "validatorVotingPower": 1166799.05,
    "hosting_provider": "VeloxServ Communications Ltd",
    "timestamp": 1667991977
  },
  {
    "asn": 59642,
    "count": 1,
    "validatorVotingPower": 1152361.25,
    "hosting_provider": "Cherry Servers NL",
    "timestamp": 1667991977
  },
  {
    "asn": 48314,
    "count": 15,
    "validatorVotingPower": 1038916.1599999999,
    "hosting_provider": "IP-Projects GmbH & Co. KG",
    "timestamp": 1667991977
  },
  {
    "asn": 58061,
    "count": 16,
    "validatorVotingPower": 950490.7399999999,
    "hosting_provider": "Unknown",
    "timestamp": 1667991977
  },
  {
    "asn": 20278,
    "count": 1,
    "validatorVotingPower": 877866.95,
    "hosting_provider": "Nexeon Technologies",
    "timestamp": 1667991977
  },
  {
    "asn": 33438,
    "count": 13,
    "validatorVotingPower": 814708.33,
    "hosting_provider": "StackPath (Highwinds)",
    "timestamp": 1667991977
  },
  {
    "asn": 29182,
    "count": 10,
    "validatorVotingPower": 685740.85,
    "hosting_provider": "ISPsystem",
    "timestamp": 1667991977
  },
  {
    "asn": 396477,
    "count": 1,
    "validatorVotingPower": 600059.89,
    "hosting_provider": "DNSnetworks",
    "timestamp": 1667991977
  },
  {
    "asn": 47447,
    "count": 1,
    "validatorVotingPower": 570333.49,
    "hosting_provider": "23M GmbH",
    "timestamp": 1667991977
  },
  {
    "asn": 3356,
    "count": 4,
    "validatorVotingPower": 556738.39,
    "hosting_provider": "Lumen AS 3356",
    "timestamp": 1667991977
  },
  {
    "asn": 397086,
    "count": 7,
    "validatorVotingPower": 555326.24,
    "hosting_provider": "Unknown",
    "timestamp": 1667991977
  },
  {
    "asn": 22439,
    "count": 8,
    "validatorVotingPower": 549618.14,
    "hosting_provider": "Unknown",
    "timestamp": 1667991977
  },
  {
    "asn": 20055,
    "count": 1,
    "validatorVotingPower": 497279.69,
    "hosting_provider": "Wholesail Networks - Main",
    "timestamp": 1667991977
  },
  {
    "asn": 13830,
    "count": 7,
    "validatorVotingPower": 473234.02999999997,
    "hosting_provider": "Nexril",
    "timestamp": 1667991977
  },
  {
    "asn": 3255,
    "count": 7,
    "validatorVotingPower": 471857.07999999996,
    "hosting_provider": "UARNet",
    "timestamp": 1667991977
  },
  {
    "asn": 212695,
    "count": 6,
    "validatorVotingPower": 439727.37999999995,
    "hosting_provider": "Unknown",
    "timestamp": 1667991977
  },
  {
    "asn": 55286,
    "count": 5,
    "validatorVotingPower": 402939.22000000003,
    "hosting_provider": "ServerMania Inc",
    "timestamp": 1667991977
  },
  {
    "asn": 206264,
    "count": 3,
    "validatorVotingPower": 384780.79000000004,
    "hosting_provider": "Amarutu Technology Ltd.",
    "timestamp": 1667991977
  },
  {
    "asn": 201730,
    "count": 1,
    "validatorVotingPower": 357841.66,
    "hosting_provider": "DataSpring",
    "timestamp": 1667991977
  },
  {
    "asn": 50304,
    "count": 2,
    "validatorVotingPower": 336717.78,
    "hosting_provider": "Blix Solutions AS",
    "timestamp": 1667991977
  },
  {
    "asn": 14576,
    "count": 5,
    "validatorVotingPower": 319235.21,
    "hosting_provider": "King Servers",
    "timestamp": 1667991977
  },
  {
    "asn": 133296,
    "count": 4,
    "validatorVotingPower": 310366.91,
    "hosting_provider": "Web Werks DataCenter",
    "timestamp": 1667991977
  },
  {
    "asn": 41668,
    "count": 4,
    "validatorVotingPower": 286310.59,
    "hosting_provider": "Unknown",
    "timestamp": 1667991977
  },
  {
    "asn": 396982,
    "count": 2,
    "validatorVotingPower": 280738.94,
    "hosting_provider": "Google Cloud",
    "timestamp": 1667991977
  },
  {
    "asn": 57043,
    "count": 4,
    "validatorVotingPower": 262811.34,
    "hosting_provider": "HOSTKEY B.V.",
    "timestamp": 1667991977
  },
  {
    "asn": 59577,
    "count": 4,
    "validatorVotingPower": 219947.77000000002,
    "hosting_provider": "ISP LinkCom",
    "timestamp": 1667991977
  },
  {
    "asn": 51167,
    "count": 4,
    "validatorVotingPower": 214775.75999999998,
    "hosting_provider": "Contabo GmbH",
    "timestamp": 1667991977
  },
  {
    "asn": 3900,
    "count": 1,
    "validatorVotingPower": 213709.84,
    "hosting_provider": "Data Foundry",
    "timestamp": 1667991977
  },
  {
    "asn": 41536,
    "count": 1,
    "validatorVotingPower": 213354.86,
    "hosting_provider": "Unknown",
    "timestamp": 1667991977
  },
  {
    "asn": 41275,
    "count": 3,
    "validatorVotingPower": 213223.14,
    "hosting_provider": "Lovitel LLC",
    "timestamp": 1667991977
  },
  {
    "asn": 35320,
    "count": 3,
    "validatorVotingPower": 211261.94,
    "hosting_provider": "ETT",
    "timestamp": 1667991977
  },
  {
    "asn": 58010,
    "count": 1,
    "validatorVotingPower": 205862.66,
    "hosting_provider": "uvensys",
    "timestamp": 1667991977
  },
  {
    "asn": 262287,
    "count": 1,
    "validatorVotingPower": 205787.37,
    "hosting_provider": "Latitude.sh_AS262287",
    "timestamp": 1667991977
  },
  {
    "asn": 398427,
    "count": 1,
    "validatorVotingPower": 200002.98,
    "hosting_provider": "MARKLEY-NETWORK-SERVICES",
    "timestamp": 1667991977
  },
  {
    "asn": 2588,
    "count": 2,
    "validatorVotingPower": 196187.06,
    "hosting_provider": "SIA Bite Latvija (old Latnet)",
    "timestamp": 1667991977
  },
  {
    "asn": 397423,
    "count": 2,
    "validatorVotingPower": 186192.5,
    "hosting_provider": "Tier.Net Technologies LLC",
    "timestamp": 1667991977
  },
  {
    "asn": 15830,
    "count": 1,
    "validatorVotingPower": 183143.3,
    "hosting_provider": "Equinix Connect",
    "timestamp": 1667991977
  },
  {
    "asn": 57128,
    "count": 2,
    "validatorVotingPower": 166933.78,
    "hosting_provider": "Ufanet Kazan Branch",
    "timestamp": 1667991977
  },
  {
    "asn": 174,
    "count": 1,
    "validatorVotingPower": 160092.47,
    "hosting_provider": "Cogent Communications, Inc.",
    "timestamp": 1667991977
  },
  {
    "asn": 13737,
    "count": 1,
    "validatorVotingPower": 154694.79,
    "hosting_provider": "INCX Global, LLC",
    "timestamp": 1667991977
  },
  {
    "asn": 55081,
    "count": 2,
    "validatorVotingPower": 147255.41,
    "hosting_provider": "24Shells Inc",
    "timestamp": 1667991977
  },
  {
    "asn": 50867,
    "count": 2,
    "validatorVotingPower": 143165.18,
    "hosting_provider": "HOSTKEY",
    "timestamp": 1667991977
  },
  {
    "asn": 3216,
    "count": 2,
    "validatorVotingPower": 138840.92,
    "hosting_provider": "VEON Group",
    "timestamp": 1667991977
  },
  {
    "asn": 57378,
    "count": 2,
    "validatorVotingPower": 138520.55,
    "hosting_provider": "Unknown",
    "timestamp": 1667991977
  },
  {
    "asn": 204770,
    "count": 2,
    "validatorVotingPower": 132415.37,
    "hosting_provider": "Unknown",
    "timestamp": 1667991977
  },
  {
    "asn": 56655,
    "count": 2,
    "validatorVotingPower": 132144.21,
    "hosting_provider": "Terrahost AS",
    "timestamp": 1667991977
  },
  {
    "asn": 22612,
    "count": 2,
    "validatorVotingPower": 131466.87,
    "hosting_provider": "Namecheap",
    "timestamp": 1667991977
  },
  {
    "asn": 25513,
    "count": 2,
    "validatorVotingPower": 131116.35,
    "hosting_provider": "MGTS",
    "timestamp": 1667991977
  },
  {
    "asn": 395839,
    "count": 2,
    "validatorVotingPower": 129293.75,
    "hosting_provider": "HOSTKEY-USA",
    "timestamp": 1667991977
  },
  {
    "asn": 30633,
    "count": 1,
    "validatorVotingPower": 120598.08,
    "hosting_provider": "LeaseWeb USA / WDC-01",
    "timestamp": 1667991977
  },
  {
    "asn": 31229,
    "count": 2,
    "validatorVotingPower": 112583.76,
    "hosting_provider": "Beyond.pl",
    "timestamp": 1667991977
  },
  {
    "asn": 48347,
    "count": 1,
    "validatorVotingPower": 105398.94,
    "hosting_provider": "MTW.RU",
    "timestamp": 1667991977
  },
  {
    "asn": 211091,
    "count": 1,
    "validatorVotingPower": 105055.5,
    "hosting_provider": "IPH",
    "timestamp": 1667991977
  },
  {
    "asn": 197235,
    "count": 2,
    "validatorVotingPower": 101699.1,
    "hosting_provider": "Avantel Samara",
    "timestamp": 1667991977
  },
  {
    "asn": 47433,
    "count": 1,
    "validatorVotingPower": 97735.84,
    "hosting_provider": "Unknown",
    "timestamp": 1667991977
  },
  {
    "asn": 39927,
    "count": 2,
    "validatorVotingPower": 92983.14,
    "hosting_provider": "E-Light-Telecom",
    "timestamp": 1667991977
  },
  {
    "asn": 42775,
    "count": 1,
    "validatorVotingPower": 92578.01,
    "hosting_provider": "ITciti",
    "timestamp": 1667991977
  },
  {
    "asn": 42989,
    "count": 2,
    "validatorVotingPower": 80076.95999999999,
    "hosting_provider": "m.it services & consulting",
    "timestamp": 1667991977
  },
  {
    "asn": 61272,
    "count": 1,
    "validatorVotingPower": 79592.18,
    "hosting_provider": "Unknown",
    "timestamp": 1667991977
  },
  {
    "asn": 12876,
    "count": 2,
    "validatorVotingPower": 79422.89,
    "hosting_provider": "Scaleway",
    "timestamp": 1667991977
  },
  {
    "asn": 60251,
    "count": 1,
    "validatorVotingPower": 73968.92,
    "hosting_provider": "CALYPSO-IT",
    "timestamp": 1667991977
  },
  {
    "asn": 50245,
    "count": 1,
    "validatorVotingPower": 72860.77,
    "hosting_provider": "Serverel",
    "timestamp": 1667991977
  },
  {
    "asn": 47440,
    "count": 1,
    "validatorVotingPower": 72796.46,
    "hosting_provider": "Business System Telecom",
    "timestamp": 1667991977
  },
  {
    "asn": 44066,
    "count": 1,
    "validatorVotingPower": 72713.99,
    "hosting_provider": "firstcolo",
    "timestamp": 1667991977
  },
  {
    "asn": 41786,
    "count": 1,
    "validatorVotingPower": 72506.24,
    "hosting_provider": "Unknown",
    "timestamp": 1667991977
  },
  {
    "asn": 51500,
    "count": 1,
    "validatorVotingPower": 72313.86,
    "hosting_provider": "Servisnet",
    "timestamp": 1667991977
  },
  {
    "asn": 29076,
    "count": 1,
    "validatorVotingPower": 71351.93,
    "hosting_provider": "Filanco AS29076",
    "timestamp": 1667991977
  },
  {
    "asn": 200000,
    "count": 1,
    "validatorVotingPower": 71243.78,
    "hosting_provider": "Hosting Ukraine",
    "timestamp": 1667991977
  },
  {
    "asn": 8220,
    "count": 1,
    "validatorVotingPower": 71094.78,
    "hosting_provider": "Colt",
    "timestamp": 1667991977
  },
  {
    "asn": 12668,
    "count": 1,
    "validatorVotingPower": 70482.26,
    "hosting_provider": "MiraLogic Telecommunication Systems",
    "timestamp": 1667991977
  },
  {
    "asn": 12993,
    "count": 1,
    "validatorVotingPower": 70019.42,
    "hosting_provider": "DEAC",
    "timestamp": 1667991977
  },
  {
    "asn": 31148,
    "count": 1,
    "validatorVotingPower": 68069.54,
    "hosting_provider": "Freenet Ltd (tm O3)",
    "timestamp": 1667991977
  },
  {
    "asn": 51604,
    "count": 1,
    "validatorVotingPower": 67178.59,
    "hosting_provider": "Unknown",
    "timestamp": 1667991977
  },
  {
    "asn": 4766,
    "count": 1,
    "validatorVotingPower": 67153.77,
    "hosting_provider": "KT Corporation (Korea Telecom)",
    "timestamp": 1667991977
  },
  {
    "asn": 56981,
    "count": 1,
    "validatorVotingPower": 66460.37,
    "hosting_provider": "Unknown",
    "timestamp": 1667991977
  },
  {
    "asn": 49824,
    "count": 1,
    "validatorVotingPower": 66290.1,
    "hosting_provider": "Astra-net",
    "timestamp": 1667991977
  },
  {
    "asn": 12213,
    "count": 1,
    "validatorVotingPower": 66135.46,
    "hosting_provider": "Cyxtera Technologies",
    "timestamp": 1667991977
  },
  {
    "asn": 35540,
    "count": 1,
    "validatorVotingPower": 65374.66,
    "hosting_provider": "OVH Telecom",
    "timestamp": 1667991977
  },
  {
    "asn": 12389,
    "count": 1,
    "validatorVotingPower": 65245.66,
    "hosting_provider": "Rostelecom",
    "timestamp": 1667991977
  },
  {
    "asn": 201201,
    "count": 1,
    "validatorVotingPower": 64980.09,
    "hosting_provider": "Datalogistics",
    "timestamp": 1667991977
  },
  {
    "asn": 59713,
    "count": 1,
    "validatorVotingPower": 64663.04,
    "hosting_provider": "Unknown",
    "timestamp": 1667991977
  },
  {
    "asn": 29944,
    "count": 1,
    "validatorVotingPower": 61131.65,
    "hosting_provider": "zColo Ashburn",
    "timestamp": 1667991977
  },
  {
    "asn": 21859,
    "count": 1,
    "validatorVotingPower": 58921.23,
    "hosting_provider": "Zenlayer Inc",
    "timestamp": 1667991977
  },
  {
    "asn": 17210,
    "count": 1,
    "validatorVotingPower": 58598.3,
    "hosting_provider": "Everywhere Wireless",
    "timestamp": 1667991977
  },
  {
    "asn": 24723,
    "count": 1,
    "validatorVotingPower": 57805.81,
    "hosting_provider": "ATMAN Basic",
    "timestamp": 1667991977
  },
  {
    "asn": 209,
    "count": 1,
    "validatorVotingPower": 51607.61,
    "hosting_provider": "Lumen AS209",
    "timestamp": 1667991977
  },
  {
    "asn": 47869,
    "count": 1,
    "validatorVotingPower": 51370.83,
    "hosting_provider": "Netrouting",
    "timestamp": 1667991977
  },
  {
    "asn": 34757,
    "count": 1,
    "validatorVotingPower": 50939.1,
    "hosting_provider": "Sibirskie Seti AS34757",
    "timestamp": 1667991977
  },
  {
    "asn": 53292,
    "count": 1,
    "validatorVotingPower": 49161.33,
    "hosting_provider": "ManagedWay Company",
    "timestamp": 1667991977
  },
  {
    "asn": 43773,
    "count": 1,
    "validatorVotingPower": 46600.1,
    "hosting_provider": "Unknown",
    "timestamp": 1667991977
  },
  {
    "asn": 34989,
    "count": 1,
    "validatorVotingPower": 38471.98,
    "hosting_provider": "Unknown",
    "timestamp": 1667991977
  },
  {
    "asn": 213220,
    "count": 1,
    "validatorVotingPower": 25110.3,
    "hosting_provider": "Unknown",
    "timestamp": 1667991977
  },
  {
    "asn": 15169,
    "count": 1,
    "validatorVotingPower": 15760.68,
    "hosting_provider": "Google LLC",
    "timestamp": 1667991977
  },
  {
    "asn": 22773,
    "count": 1,
    "validatorVotingPower": 311.38,
    "hosting_provider": "Cox Communications",
    "timestamp": 1667991977
  },
  {
    "asn": 20473,
    "count": 1,
    "validatorVotingPower": 160.66,
    "hosting_provider": "The Constant Company, LLC",
    "timestamp": 1667991977
  },
  {
    "asn": 56418,
    "count": 1,
    "validatorVotingPower": 31.82,
    "hosting_provider": "SkynetCom",
    "timestamp": 1667991977
  },
  {
    "asn": 29014,
    "count": 1,
    "validatorVotingPower": 0.01,
    "hosting_provider": "ScaleUp Technologies",
    "timestamp": 1667991977
  }
]