[{"name": "Zilliqa", "symbol": "ZIL", "timestamp": "2022-08-29 03:11:54", "validators": 21, "nodes": 2158, "total": 2179, "source": "https://viewblock.io/zilliqa", "market_cap_rank": 82, "market_cap": 528195804, "volume": 89990391, "nodediff": -242, "nodediffper": -10.08, "validatordiff": 0, "validatordiffper": 0, "totaldiff": -242, "totaldiffper": -10.0, "rank": 1, "created": "2022-08-29 03:12:18", "chaintype": "PoS"}, {"name": "Decred", "symbol": "DCR", "timestamp": "2022-08-29 03:00:48", "validators": 0, "nodes": 25, "total": 25, "source": "https://dcrstats.com/map", "market_cap_rank": 102, "market_cap": 394718570, "volume": 1972975, "nodediff": -1, "nodediffper": -3.85, "validatordiff": 0, "validatordiffper": 0, "totaldiff": -1, "totaldiffper": -3.85, "rank": 2, "created": "2022-08-29 03:12:18", "chaintype": "PoW"}, {"name": "IOTA", "symbol": "MIOTA", "timestamp": "2022-08-29 03:07:57", "validators": 0, "nodes": 392, "total": 392, "source": "https://thetangle.org/nodes", "market_cap_rank": 61, "market_cap": 764982642, "volume": 13217665, "nodediff": -4, "nodediffper": -1.01, "validatordiff": 0, "validatordiffper": 0, "totaldiff": -4, "totaldiffper": -1.01, "rank": 3, "created": "2022-08-29 03:12:18", "chaintype": "PoW"}, {"name": "Zcash", "symbol": "ZEC", "timestamp": "2022-08-29 03:12:18", "validators": 0, "nodes": 8459, "total": 8459, "source": "https://blockchair.com/zcash/nodes", "market_cap_rank": 59, "market_cap": 789397772, "volume": 35574809, "nodediff": -7, "nodediffper": -0.08, "validatordiff": 0, "validatordiffper": 0, "totaldiff": -7, "totaldiffper": -0.08, "rank": 4, "created": "2022-08-29 03:12:18", "chaintype": "PoW"}, {"name": "Ethereum", "symbol": "ETH", "timestamp": "2022-08-29 03:03:38", "validators": 417855, "nodes": 8120, "total": 425975, "source": "https://beaconcha.in", "market_cap_rank": 2, "market_cap": 174293021472, "volume": 11376950093, "nodediff": 0, "nodediffper": 0, "validatordiff": 0, "validatordiffper": 0, "totaldiff": 0, "totaldiffper": 0, "rank": 5, "created": "2022-08-29 03:12:18", "chaintype": "PoS"}]